ygModbus/__init__.py
ygModbus/cli.py
ygModbus/client.py
ygModbus/main.py
ygModbus/server.py
ygModbus-0.0.14.dist-info/METADATA
ygModbus-0.0.14.dist-info/WHEEL
ygModbus-0.0.14.dist-info/entry_points.txt
ygModbus-0.0.14.dist-info/top_level.txt
ygModbus-0.0.14.dist-info/RECORD
