Metadata-Version: 2.1
Name: ygModbus
Version: 0.0.14
Summary: simple Modebus client and server test by response of random number
Home-page: https://github.com/devggu/
Author: devggu
Author-email: pshnb123@gmail.com
Keywords: modebus,pshn123,devggu,TCP,server,client
Classifier: Programming Language :: Python :: 3.6
Classifier: Programming Language :: Python :: 3.7
Classifier: Programming Language :: Python :: 3.8
Classifier: Programming Language :: Python :: 3.9
Requires-Python: >=3.6
Requires-Dist: pyModbusTCP
Requires-Dist: schedule
Requires-Dist: pandas
Requires-Dist: numpy
